mailcheck/__init__.py
mailcheck/mailcheck.py
mailcheck-1.0.0.dist-info/METADATA
mailcheck-1.0.0.dist-info/WHEEL
mailcheck-1.0.0.dist-info/top_level.txt
mailcheck-1.0.0.dist-info/RECORD
