Metadata-Version: 2.1
Name: mailcheck
Version: 1.0.0
Summary: Python wrapper for the MailCheck.ai API
Author: Nemuel Wainaina
